miu_examples/__init__.py
miu_examples/mcp_client.py
miu_examples/multi_agent.py
miu_examples/multi_provider.py
miu_examples/rag_agent.py
miu_examples/simple_agent.py
miu_examples/tool_usage.py
miu_examples-1.0.0.dist-info/METADATA
miu_examples-1.0.0.dist-info/WHEEL
miu_examples-1.0.0.dist-info/RECORD
