Metadata-Version: 2.4
Name: miu-examples
Version: 1.0.0
Summary: Example applications using miu-core
Requires-Python: >=3.11
Requires-Dist: miu-core[all]
Provides-Extra: rag
Requires-Dist: qdrant-client>=1.12; extra == 'rag'
